{"type": "statement", "message": {"id": "856683968384860190", "type": 0, "content": "I discovered about 5 years ago that I'm lactose intolerant \ud83d\ude2d So I've since lived a cheese-less life. Nothing wrong with that! Just, I miss cheese and mac n' cheese \ud83d\ude26", "channel_id": "856680590857076767", "author": {"id": "786370144120209478", "username": "Neleimour", "avatar": "a_e45fb561aa69f58bd9b9e4cc587a503e", "discriminator": "6254", "public_flags": 0}, "attachments": [], "embeds": [], "mentions": [], "mention_roles": [], "pinned": false, "mention_everyone": false, "tts": false, "timestamp": "2021-06-21T23:56:14.481000+00:00", "edited_timestamp": null, "flags": 0, "components": [], "hit": true}}